[
  {
    "word": "well-being",
    "wordZh": "福祉",
    "type": "multiple-choice",
    "question": "What does 'well-being' mean?",
    "questionZh": "‘福祉’ 的意思是什么？",
    "options": ["Illness", "State of being healthy and happy", "Work", "Sadness"],
    "optionsZh": ["疾病", "健康和幸福的状态", "工作", "悲伤"],
    "correct": "State of being healthy and happy",
    "correctZh": "健康和幸福的状态",
    "example": "Well-being is important for life.",
    "exampleZh": "福祉对生活很重要。"
  },
  {
    "word": "well-being",
    "wordZh": "福祉",
    "type": "select-all",
    "question": "What promotes 'well-being'?",
    "questionZh": "什么促进 ‘福祉’？",
    "options": ["Stress", "Exercise", "Healthy diet", "Isolation", "Sleep"],
    "optionsZh": ["压力", "运动", "健康饮食", "孤立", "睡眠"],
    "correct": ["2", "3", "5"],
    "correctZh": ["运动", "健康饮食", "睡眠"],
    "example": "Exercise promotes well-being.",
    "exampleZh": "运动促进福祉。"
  },
  {
    "word": "sedentary",
    "wordZh": "久坐",
    "type": "multiple-choice",
    "question": "What does 'sedentary' mean?",
    "questionZh": "‘久坐’ 的意思是什么？",
    "options": ["Active", "Sitting a lot", "Running", "Eating"],
    "optionsZh": ["活跃", "久坐", "跑步", "吃饭"],
    "correct": "Sitting a lot",
    "correctZh": "久坐",
    "example": "A sedentary lifestyle harms health.",
    "exampleZh": "久坐的生活方式损害健康。"
  },
  {
    "word": "sedentary",
    "wordZh": "久坐",
    "type": "true-false",
    "question": "Sedentary habits increase health risks.",
    "questionZh": "久坐习惯增加健康风险。",
    "options": ["True", "False"],
    "optionsZh": ["正确", "错误"],
    "correct": "True",
    "correctZh": "正确",
    "example": "Sedentary work causes back pain.",
    "exampleZh": "久坐工作导致背痛。"
  },
  {
    "word": "vitality",
    "wordZh": "活力",
    "type": "multiple-choice",
    "question": "What does 'vitality' mean?",
    "questionZh": "‘活力’ 的意思是什么？",
    "options": ["Weakness", "Energy and strength", "Illness", "Tiredness"],
    "optionsZh": ["虚弱", "能量和力量", "疾病", "疲倦"],
    "correct": "Energy and strength",
    "correctZh": "能量和力量",
    "example": "Vitality comes from exercise.",
    "exampleZh": "活力来自运动。"
  },
  {
    "word": "vitality",
    "wordZh": "活力",
    "type": "select-all",
    "question": "What boosts 'vitality'?",
    "questionZh": "什么增强 ‘活力’？",
    "options": ["Sitting", "Healthy food", "Exercise", "Stress", "Sleep"],
    "optionsZh": ["久坐", "健康食品", "运动", "压力", "睡眠"],
    "correct": ["2", "3", "5"],
    "correctZh": ["健康食品", "运动", "睡眠"],
    "example": "Sleep boosts vitality.",
    "exampleZh": "睡眠增强活力。"
  },
  {
    "word": "prevention",
    "wordZh": "预防",
    "type": "multiple-choice",
    "question": "What does 'prevention' mean?",
    "questionZh": "‘预防’ 的意思是什么？",
    "options": ["Treatment", "Stopping something bad", "Illness", "Work"],
    "optionsZh": ["治疗", "阻止坏事", "疾病", "工作"],
    "correct": "Stopping something bad",
    "correctZh": "阻止坏事",
    "example": "Prevention reduces illness.",
    "exampleZh": "预防减少疾病。"
  },
  {
    "word": "prevention",
    "wordZh": "预防",
    "type": "true-false",
    "question": "Prevention is better than cure.",
    "questionZh": "预防胜于治疗。",
    "options": ["True", "False"],
    "optionsZh": ["正确", "错误"],
    "correct": "True",
    "correctZh": "正确",
    "example": "Prevention saves health costs.",
    "exampleZh": "预防节省健康成本。"
  },
  {
    "word": "therapy",
    "wordZh": "疗法",
    "type": "multiple-choice",
    "question": "What does 'therapy' mean?",
    "questionZh": "‘疗法’ 的意思是什么？",
    "options": ["Food", "Treatment for health", "Game", "Work"],
    "optionsZh": ["食物", "健康治疗", "游戏", "工作"],
    "correct": "Treatment for health",
    "correctZh": "健康治疗",
    "example": "Therapy helps mental health.",
    "exampleZh": "疗法帮助心理健康。"
  },
  {
    "word": "therapy",
    "wordZh": "疗法",
    "type": "select-all",
    "question": "What involves 'therapy'?",
    "questionZh": "‘疗法’ 涉及什么？",
    "options": ["Eating", "Counseling", "Exercise", "Driving", "Talking"],
    "optionsZh": ["吃饭", "咨询", "运动", "开车", "谈话"],
    "correct": ["2", "3", "5"],
    "correctZh": ["咨询", "运动", "谈话"],
    "example": "Counseling is a therapy.",
    "exampleZh": "咨询是一种疗法。"
  },
  {
    "word": "mindfulness",
    "wordZh": "正念",
    "type": "multiple-choice",
    "question": "What does 'mindfulness' mean?",
    "questionZh": "‘正念’ 的意思是什么？",
    "options": ["Forgetfulness", "Focusing on the present", "Stress", "Work"],
    "optionsZh": ["健忘", "专注于现在", "压力", "工作"],
    "correct": "Focusing on the present",
    "correctZh": "专注于现在",
    "example": "Mindfulness reduces stress.",
    "exampleZh": "正念减少压力。"
  },
  {
    "word": "mindfulness",
    "wordZh": "正念",
    "type": "true-false",
    "question": "Mindfulness improves mental health.",
    "questionZh": "正念改善心理健康。",
    "options": ["True", "False"],
    "optionsZh": ["正确", "错误"],
    "correct": "True",
    "correctZh": "正确",
    "example": "I practice mindfulness daily.",
    "exampleZh": "我每天练习正念。"
  },
  {
    "word": "endurance",
    "wordZh": "耐力",
    "type": "multiple-choice",
    "question": "What does 'endurance' mean?",
    "questionZh": "‘耐力’ 的意思是什么？",
    "options": ["Weakness", "Ability to keep going", "Illness", "Rest"],
    "optionsZh": ["虚弱", "持续进行的能力", "疾病", "休息"],
    "correct": "Ability to keep going",
    "correctZh": "持续进行的能力",
    "example": "Endurance improves fitness.",
    "exampleZh": "耐力提高健身水平。"
  },
  {
    "word": "endurance",
    "wordZh": "耐力",
    "type": "select-all",
    "question": "What builds 'endurance'?",
    "questionZh": "什么建立 ‘耐力’？",
    "options": ["Sitting", "Running", "Swimming", "Watching TV", "Training"],
    "optionsZh": ["久坐", "跑步", "游泳", "看电视", "训练"],
    "correct": ["2", "3", "5"],
    "correctZh": ["跑步", "游泳", "训练"],
    "example": "Running builds endurance.",
    "exampleZh": "跑步建立耐力。"
  },
  {
    "word": "nutritionist",
    "wordZh": "营养师",
    "type": "multiple-choice",
    "question": "What does 'nutritionist' mean?",
    "questionZh": "‘营养师’ 的意思是什么？",
    "options": ["Teacher", "Diet expert", "Driver", "Chef"],
    "optionsZh": ["老师", "饮食专家", "司机", "厨师"],
    "correct": "Diet expert",
    "correctZh": "饮食专家",
    "example": "A nutritionist gives diet advice.",
    "exampleZh": "营养师提供饮食建议。"
  },
  {
    "word": "nutritionist",
    "wordZh": "营养师",
    "type": "true-false",
    "question": "Nutritionists help improve health.",
    "questionZh": "营养师帮助改善健康。",
    "options": ["True", "False"],
    "optionsZh": ["正确", "错误"],
    "correct": "True",
    "correctZh": "正确",
    "example": "I consult a nutritionist.",
    "exampleZh": "我咨询营养师。"
  },
  {
    "word": "regimen",
    "wordZh": "养生法",
    "type": "multiple-choice",
    "question": "What does 'regimen' mean?",
    "questionZh": "‘养生法’ 的意思是什么？",
    "options": ["Food", "Planned routine", "Game", "Work"],
    "optionsZh": ["食物", "计划的日常", "游戏", "工作"],
    "correct": "Planned routine",
    "correctZh": "计划的日常",
    "example": "A regimen improves health.",
    "exampleZh": "养生法改善健康。"
  },
  {
    "word": "regimen",
    "wordZh": "养生法",
    "type": "select-all",
    "question": "What is part of a health 'regimen'?",
    "questionZh": "健康 ‘养生法’ 包括什么？",
    "options": ["Watching TV", "Exercise", "Healthy diet", "Stress", "Sleep"],
    "optionsZh": ["看电视", "运动", "健康饮食", "压力", "睡眠"],
    "correct": ["2", "3", "5"],
    "correctZh": ["运动", "健康饮食", "睡眠"],
    "example": "Exercise is part of my regimen.",
    "exampleZh": "运动是我养生法的一部分。"
  },
  {
    "word": "resilience",
    "wordZh": "韧性",
    "type": "multiple-choice",
    "question": "What does 'resilience' mean?",
    "questionZh": "‘韧性’ 的意思是什么？",
    "options": ["Weakness", "Ability to recover", "Illness", "Fear"],
    "optionsZh": ["虚弱", "恢复的能力", "疾病", "恐惧"],
    "correct": "Ability to recover",
    "correctZh": "恢复的能力",
    "example": "Resilience helps mental health.",
    "exampleZh": "韧性帮助心理健康。"
  },
  {
    "word": "resilience",
    "wordZh": "韧性",
    "type": "true-false",
    "question": "Resilience reduces stress effects.",
    "questionZh": "韧性减少压力影响。",
    "options": ["True", "False"],
    "optionsZh": ["正确", "错误"],
    "correct": "True",
    "correctZh": "正确",
    "example": "I build resilience through therapy.",
    "exampleZh": "我通过疗法建立韧性。"
  },
  {
    "word": "hydration",
    "wordZh": "水合",
    "type": "multiple-choice",
    "question": "What does 'hydration' mean?",
    "questionZh": "‘水合’ 的意思是什么？",
    "options": ["Eating", "Keeping body water levels", "Sleeping", "Work"],
    "optionsZh": ["吃饭", "保持身体水分水平", "睡觉", "工作"],
    "correct": "Keeping body water levels",
    "correctZh": "保持身体水分水平",
    "example": "Hydration supports health.",
    "exampleZh": "水合支持健康。"
  },
  {
    "word": "hydration",
    "wordZh": "水合",
    "type": "select-all",
    "question": "What helps 'hydration'?",
    "questionZh": "什么帮助 ‘水合’？",
    "options": ["Candy", "Water", "Juice", "Chips", "Tea"],
    "optionsZh": ["糖果", "水", "果汁", "薯片", "茶"],
    "correct": ["2", "3", "5"],
    "correctZh": ["水", "果汁", "茶"],
    "example": "Water helps hydration.",
    "exampleZh": "水帮助水合。"
  },
  {
    "word": "longevity",
    "wordZh": "长寿",
    "type": "multiple-choice",
    "question": "What does 'longevity' mean?",
    "questionZh": "‘长寿’ 的意思是什么？",
    "options": ["Short life", "Long life", "Illness", "Work"],
    "optionsZh": ["短寿", "长寿", "疾病", "工作"],
    "correct": "Long life",
    "correctZh": "长寿",
    "example": "Longevity depends on lifestyle.",
    "exampleZh": "长寿取决于生活方式。"
  },
  {
    "word": "longevity",
    "wordZh": "长寿",
    "type": "true-false",
    "question": "Longevity is linked to healthy habits.",
    "questionZh": "长寿与健康习惯有关。",
    "options": ["True", "False"],
    "optionsZh": ["正确", "错误"],
    "correct": "True",
    "correctZh": "正确",
    "example": "Healthy diet promotes longevity.",
    "exampleZh": "健康饮食促进长寿。"
  },
  {
    "word": "opinion",
    "wordZh": "观点",
    "type": "multiple-choice",
    "question": "Which phrase expresses your view on health and lifestyle?",
    "questionZh": "哪个短语表达你对健康和生活方式的看法？",
    "options": ["As a result", "I believe", "Whereas", "Tackle"],
    "optionsZh": ["因此", "我相信", "然而", "解决"],
    "correct": "I believe",
    "correctZh": "我相信",
    "example": "I believe mindfulness improves health.",
    "exampleZh": "我相信正念改善健康。"
  },
  {
    "word": "solution",
    "wordZh": "解决方案",
    "type": "multiple-choice",
    "question": "Which phrase suggests solving lifestyle health issues?",
    "questionZh": "哪个短语建议解决生活方式健康问题？",
    "options": ["On the contrary", "Tackle", "I concur", "It seems to me"],
    "optionsZh": ["相反", "解决", "我同意", "在我看来"],
    "correct": "Tackle",
    "correctZh": "解决",
    "example": "We should tackle sedentary habits with exercise.",
    "exampleZh": "我们应该通过运动解决久坐习惯。"
  },
  {
    "word": "opinion",
    "wordZh": "观点",
    "type": "true-false",
    "question": "‘I believe’ is used to express a personal opinion on health practices.",
    "questionZh": "‘我相信’ 用于表达对健康实践的个人意见。",
    "options": ["True", "False"],
    "optionsZh": ["正确", "错误"],
    "correct": "True",
    "correctZh": "正确",
    "example": "I believe hydration supports longevity.",
    "exampleZh": "我相信水合支持长寿。"
  },
  {
    "word": "opinion",
    "wordZh": "观点",
    "type": "true-false",
    "question": "‘Owing to’ shows the result of a health action.",
    "questionZh": "‘由于’ 显示健康行动的结果。",
    "options": ["True", "False"],
    "optionsZh": ["正确", "错误"],
    "correct": "False",
    "correctZh": "错误",
    "example": "Owing to poor diet, vitality decreases.",
    "exampleZh": "由于饮食不良，活力下降。"
  },
  {
    "word": "opinion",
    "wordZh": "观点",
    "type": "select-all",
    "question": "Which phrases express opinions on health practices?",
    "questionZh": "哪些短语表达健康实践的意见？",
    "options": ["I believe", "As a result", "In my view", "Tackle", "Owing to"],
    "optionsZh": ["我相信", "因此", "在我看来", "解决", "由于"],
    "correct": ["1", "3"],
    "correctZh": ["我相信", "在我看来"],
    "example": "I believe therapy helps resilience.",
    "exampleZh": "我相信疗法有助于韧性。"
  },
  {
    "word": "solution",
    "wordZh": "解决方案",
    "type": "select-all",
    "question": "Which phrases suggest solutions for health issues?",
    "questionZh": "哪些短语建议解决健康问题的方案？",
    "options": ["I believe", "Tackle", "As a result", "Propose", "Whereas"],
    "optionsZh": ["我相信", "解决", "因此", "提出", "然而"],
    "correct": ["2", "4"],
    "correctZh": ["解决", "提出"],
    "example": "We propose a fitness regimen.",
    "exampleZh": "我们提出健身养生法。"
  }
]
